bitcoin_safe/__init__.py
bitcoin_safe/__main__.py
bitcoin_safe/category_info.py
bitcoin_safe/config.py
bitcoin_safe/descriptor_export_tools.py
bitcoin_safe/descriptors.py
bitcoin_safe/dynamic_lib_load.py
bitcoin_safe/execute_config.py
bitcoin_safe/fx.py
bitcoin_safe/gui/__init__.py
bitcoin_safe/gui/icons/add-person.svg
bitcoin_safe/gui/icons/add-person_darkmode.svg
bitcoin_safe/gui/icons/bitcoin-bitcoin.svg
bitcoin_safe/gui/icons/bitcoin-regtest.svg
bitcoin_safe/gui/icons/bitcoin-signet.svg
bitcoin_safe/gui/icons/bitcoin-testnet.svg
bitcoin_safe/gui/icons/block-explorer.svg
bitcoin_safe/gui/icons/camera.svg
bitcoin_safe/gui/icons/camera_darkmode.svg
bitcoin_safe/gui/icons/checkmark.svg
bitcoin_safe/gui/icons/clip.svg
bitcoin_safe/gui/icons/clip_darkmode.svg
bitcoin_safe/gui/icons/clock1.png
bitcoin_safe/gui/icons/clock2.png
bitcoin_safe/gui/icons/clock3.png
bitcoin_safe/gui/icons/clock4.png
bitcoin_safe/gui/icons/clock5.png
bitcoin_safe/gui/icons/cloud-sync-off.svg
bitcoin_safe/gui/icons/cloud-sync-off_darkmode.svg
bitcoin_safe/gui/icons/cloud-sync.svg
bitcoin_safe/gui/icons/cloud-sync_darkmode.svg
bitcoin_safe/gui/icons/confirmed.svg
bitcoin_safe/gui/icons/copy.png
bitcoin_safe/gui/icons/csv-file.svg
bitcoin_safe/gui/icons/csv-file_darkmode.svg
bitcoin_safe/gui/icons/descriptor-backup.svg
bitcoin_safe/gui/icons/dice.svg
bitcoin_safe/gui/icons/dice_darkmode.svg
bitcoin_safe/gui/icons/distribute-multisig.svg
bitcoin_safe/gui/icons/distribute-multisigsig-export.svgz
bitcoin_safe/gui/icons/distribute-singlesig-export.svgz
bitcoin_safe/gui/icons/distribute-singlesig.svg
bitcoin_safe/gui/icons/download.png
bitcoin_safe/gui/icons/earth.svg
bitcoin_safe/gui/icons/error.png
bitcoin_safe/gui/icons/exchange.svg
bitcoin_safe/gui/icons/file.png
bitcoin_safe/gui/icons/flows.svg
bitcoin_safe/gui/icons/hardware_signers/bitbox02-icon.svg
bitcoin_safe/gui/icons/hardware_signers/bitbox02-sticker.svg
bitcoin_safe/gui/icons/hardware_signers/cobo-icon.svg
bitcoin_safe-1.0.6.dist-info/LICENSE
bitcoin_safe-1.0.6.dist-info/METADATA
bitcoin_safe-1.0.6.dist-info/WHEEL
bitcoin_safe-1.0.6.dist-info/RECORD
