Metadata-Version: 2.1
Name: bitcoin-safe
Version: 1.0.6
Summary: A bitcoin savings wallet for the entire family.
Home-page: https://www.bitcoin-safe.org
License: GPL-3.0
Author: andreasgriffin
Author-email: andreasgriffin@proton.me
Requires-Python: >=3.10,<3.13
Classifier: License :: OSI Approved :: GNU General Public License v3 (GPLv3)
Classifier: Programming Language :: Python :: 3
Classifier: Programming Language :: Python :: 3.10
Classifier: Programming Language :: Python :: 3.11
Classifier: Programming Language :: Python :: 3.12
Requires-Dist: appdirs (>=1.4.4,<2.0.0)
Requires-Dist: bdkpython (>=0.32.0,<0.33.0)
Requires-Dist: bitcoin-nostr-chat (>=0.6.2,<0.7.0)
Requires-Dist: bitcoin-qr-tools (>=1.0.4,<2.0.0)
Requires-Dist: bitcoin-usb (>=0.7.8,<0.8.0)
Requires-Dist: cbor2 (>=5.6.0,<6.0.0)
Requires-Dist: cryptography (>=43.0.1,<44.0.0)
Requires-Dist: fpdf2 (>=2.7.4,<3.0.0)
Requires-Dist: hwi (>=2.3.1)
Requires-Dist: numpy (==2.2.1)
Requires-Dist: pgpy (>=0.6.0,<0.7.0)
Requires-Dist: pyqt6 (>=6.6.1,<7.0.0)
Requires-Dist: pyqt6-charts (>=6.6.0,<7.0.0)
Requires-Dist: pysocks (>=1.7.1,<2.0.0)
Requires-Dist: python-gnupg (>=0.5.2,<0.6.0)
Requires-Dist: pyyaml (>=6.0,<7.0)
Requires-Dist: reportlab (==4.0.8)
Requires-Dist: requests (>=2.31.0,<3.0.0)
